README.rst
setup.py
axerflow/__init__.py
axerflow/_spark_autologging.py
axerflow/cli.py
axerflow/data.py
axerflow/db.py
axerflow/exceptions.py
axerflow/experiments.py
axerflow/fastai.py
axerflow/gluon.py
axerflow/h2o.py
axerflow/keras.py
axerflow/lightgbm.py
axerflow/mleap.py
axerflow/onnx.py
axerflow/runs.py
axerflow/sklearn.py
axerflow/spacy.py
axerflow/spark.py
axerflow/tensorflow.py
axerflow/version.py
axerflow/xgboost.py
axerflow.egg-info/PKG-INFO
axerflow.egg-info/SOURCES.txt
axerflow.egg-info/dependency_links.txt
axerflow.egg-info/entry_points.txt
axerflow.egg-info/not-zip-safe
axerflow.egg-info/requires.txt
axerflow.egg-info/top_level.txt
axerflow/azureml/__init__.py
axerflow/azureml/cli.py
axerflow/entities/__init__.py
axerflow/entities/_axerflow_object.py
axerflow/entities/experiment.py
axerflow/entities/experiment_tag.py
axerflow/entities/file_info.py
axerflow/entities/lifecycle_stage.py
axerflow/entities/metric.py
axerflow/entities/param.py
axerflow/entities/run.py
axerflow/entities/run_data.py
axerflow/entities/run_info.py
axerflow/entities/run_status.py
axerflow/entities/run_tag.py
axerflow/entities/source_type.py
axerflow/entities/view_type.py
axerflow/entities/model_registry/__init__.py
axerflow/entities/model_registry/_model_registry_entity.py
axerflow/entities/model_registry/model_version.py
axerflow/entities/model_registry/model_version_stages.py
axerflow/entities/model_registry/model_version_status.py
axerflow/entities/model_registry/registered_model.py
axerflow/models/__init__.py
axerflow/models/cli.py
axerflow/models/docker_utils.py
axerflow/models/flavor_backend.py
axerflow/models/flavor_backend_registry.py
axerflow/models/model.py
axerflow/models/signature.py
axerflow/models/utils.py
axerflow/models/container/.ptp-sync-folder
axerflow/models/container/__init__.py
axerflow/models/container/__pycache__/.ptp-sync-folder
axerflow/models/container/__pycache__/__init__.cpython-36.pyc
axerflow/models/container/__pycache__/__init__.cpython-37.pyc
axerflow/models/container/scoring_server/.ptp-sync-folder
axerflow/models/container/scoring_server/__init__.py
axerflow/models/container/scoring_server/nginx.conf
axerflow/models/container/scoring_server/wsgi.py
